kya_newsreader/__init__.py
kya_newsreader/constant.py
kya_newsreader/exceptions.py
kya_newsreader/news_crawler.py
kya_newsreader/news_url_getter.py
KyaNewsScraper-1.0.5.dist-info/LICENSE
KyaNewsScraper-1.0.5.dist-info/METADATA
KyaNewsScraper-1.0.5.dist-info/WHEEL
KyaNewsScraper-1.0.5.dist-info/top_level.txt
KyaNewsScraper-1.0.5.dist-info/RECORD
