Metadata-Version: 2.1
Name: KyaNewsScraper
Version: 1.0.5
Summary: A Python-based tool for scraping news articles from various sources, using different techniques.
Home-page: https://github.com/yourgithubusername/newscrawler
Author: Kya
Keywords: news,web scraping,article scraping,news scraping
Classifier: Development Status :: 3 - Alpha
Classifier: Intended Audience :: Developers
Classifier: Natural Language :: English
Classifier: Operating System :: OS Independent
Classifier: Programming Language :: Python :: 3
Classifier: Programming Language :: Python :: 3.7
Classifier: Programming Language :: Python :: 3.8
Classifier: Programming Language :: Python :: 3.9
Classifier: License :: OSI Approved :: MIT License
Requires-Python: >=3.6
License-File: LICENSE
Requires-Dist: requests
Requires-Dist: selenium
Requires-Dist: newspaper3k
Requires-Dist: selenium-stealth
Requires-Dist: beautifulsoup4
